fraggle/__init__.py
fraggle-0.1.5.dist-info/METADATA
fraggle-0.1.5.dist-info/WHEEL
fraggle-0.1.5.dist-info/entry_points.txt
fraggle-0.1.5.dist-info/RECORD
