Metadata-Version: 2.4
Name: fraggle
Version: 0.1.5
Summary: A simple RAG API - build a question and answer interface to your own content in minutes
Project-URL: Home, https://github.com/tomdyson/fraggle
Author-email: Tom Dyson <tom@torchbox.com>
License: MIT
Requires-Python: >=3.12
Requires-Dist: any-llm-sdk[anthropic,openai]>=0.1.0
Requires-Dist: faiss-cpu>=1.8.0
Requires-Dist: fastapi>=0.115.0
Requires-Dist: langchain-community>=0.3.0
Requires-Dist: langchain-openai>=0.3.0
Requires-Dist: langchain-text-splitters>=0.3.0
Requires-Dist: langchain>=0.3.0
Requires-Dist: sse-starlette>=2.1.0
Requires-Dist: tiktoken>=0.7.0
Requires-Dist: typer>=0.12.0
Requires-Dist: uvicorn[standard]>=0.30.0
